nn/__init__.py
nn/conv_net.py
nn/neural_network.py
nn_library-1.1.1.dist-info/METADATA
nn_library-1.1.1.dist-info/WHEEL
nn_library-1.1.1.dist-info/top_level.txt
nn_library-1.1.1.dist-info/RECORD
