Metadata-Version: 2.1
Name: nn-library
Version: 1.1.1
Summary: A library for building neural networks.
Home-page: UNKNOWN
Author: Vitalii Cherednyk
Author-email: vitalijcerednik@gmail.com
License: UNKNOWN
Platform: UNKNOWN
Requires-Python: >=3.6
